gym_gidwumpus/__init__.py
gym_gidwumpus-1.5.dist-info/LICENSE.txt
gym_gidwumpus-1.5.dist-info/METADATA
gym_gidwumpus-1.5.dist-info/WHEEL
gym_gidwumpus-1.5.dist-info/top_level.txt
gym_gidwumpus-1.5.dist-info/RECORD
