Metadata-Version: 2.1
Name: gym-gidwumpus
Version: 1.5
Summary: This is an environment for the wumpus world that you can reference as an openai gym environment.
Home-page: https://github.com/Gid8/gym-gidwumpus
Author: Gideon Jacobus Pieterse
Author-email: Gideondeonjacobus@gmail.com
License: MIT
Download-URL: https://github.com/Gid8/gym-gidwumpus/archive/1.5.tar.gz
Keywords: openai,ai,reinforcement,learning,reinforcement learning,wimpus,env,environment,machine,machine learning
Platform: UNKNOWN
Classifier: Development Status :: 5 - Production/Stable
Classifier: Intended Audience :: Developers
Classifier: Topic :: Software Development :: Build Tools
Classifier: License :: OSI Approved :: MIT License
Classifier: Programming Language :: Python :: 3
Classifier: Programming Language :: Python :: 3.4
Classifier: Programming Language :: Python :: 3.5
Classifier: Programming Language :: Python :: 3.6
Classifier: Programming Language :: Python :: 3.7
Requires-Dist: gym
Requires-Dist: numpy
